setup.cfg
setup.py
infEGE/__init__.py
infEGE/algebra_logics.py
infEGE/combinatorics.py
infEGE/constants.py
infEGE/decorators.py
infEGE/exceptions.py
infEGE/lists_and_other.py
infEGE/mathematics.py
infEGE/string.py
infEGE/system_count.py
infEGE.egg-info/PKG-INFO
infEGE.egg-info/SOURCES.txt
infEGE.egg-info/dependency_links.txt
infEGE.egg-info/top_level.txt