Metadata-Version: 2.1
Name: infEGE
Version: 1.7
Summary: Библиотека для ЕГЭ по информатике
Home-page: https://github.com/Ilya484/infEGE
Author: Ilya484
Author-email: ucdo854@kemcdo.ru
License: UNKNOWN
Platform: UNKNOWN
Classifier: Programming Language :: Python :: 3
